snakeshell/__init__.py
snakeshell/__main__.py
snakeshell/console/__init__.py
snakeshell/console/command_line.py
snakeshell/console/cursor.py
snakeshell/console/prompt.py
snakeshell/console/stream.py
snakeshell/grammar.py
snakeshell/parser.py
snakeshell/shell.py
snakeshell/tree.py
cobrashell-0.0.2.dist-info/LICENSE
cobrashell-0.0.2.dist-info/METADATA
cobrashell-0.0.2.dist-info/WHEEL
cobrashell-0.0.2.dist-info/entry_points.txt
cobrashell-0.0.2.dist-info/RECORD
