Metadata-Version: 2.1
Name: cobrashell
Version: 0.0.2
Summary: Unix Shell written in Python3
Home-page: https://github.com/G000D1ESS/snakeshell.git
License: MIT
Keywords: unix,shell
Author: G000D1ESS
Author-email: wherenodarkness@mail.ru
Requires-Python: >=3.12,<4.0
Classifier: Development Status :: 1 - Planning
Classifier: License :: OSI Approved :: MIT License
Classifier: Programming Language :: Python :: 3
Classifier: Programming Language :: Python :: 3.12
Classifier: Programming Language :: Python :: 3.13
Classifier: Topic :: System :: Shells
Requires-Dist: TatSu (>=5.12.1,<6.0.0)
Project-URL: Repository, https://github.com/G000D1ESS/snakeshell.git
